setup.py
check_rabbitmq_queues/__init__.py
check_rabbitmq_queues/check.py
check_rabbitmq_queues.egg-info/PKG-INFO
check_rabbitmq_queues.egg-info/SOURCES.txt
check_rabbitmq_queues.egg-info/dependency_links.txt
check_rabbitmq_queues.egg-info/entry_points.txt
check_rabbitmq_queues.egg-info/requires.txt
check_rabbitmq_queues.egg-info/top_level.txt