Metadata-Version: 1.0
Name: check-rabbitmq-queues
Version: 1.0.1
Summary: Package for checking current length of RabbitMQ queues.
Home-page: UNKNOWN
Author: Opera Services Team
Author-email: svc-code@opera.com
License: UNKNOWN
Platform: UNKNOWN
